fjmvlib/__init__.py
fjmvlib/fjmvlib.py
fjmvlib-0.5.dist-info/LICENSE
fjmvlib-0.5.dist-info/METADATA
fjmvlib-0.5.dist-info/WHEEL
fjmvlib-0.5.dist-info/top_level.txt
fjmvlib-0.5.dist-info/RECORD
