Metadata-Version: 2.1
Name: fjmvlib
Version: 0.5
Summary: A small package with helper functions to validate Fire Jumper Programmability Mission submissions.
Home-page: https://github.com/oxsannikova/fjmvlib
Author: Oxana Sannikova
Author-email: osanniko@cisco.com
License: UNKNOWN
Download-URL: https://github.com/oxsannikova/fjmvlib/archive/v_06.tar.gz
Platform: UNKNOWN
Classifier: Development Status :: 3 - Alpha
Classifier: Intended Audience :: Developers
Classifier: Topic :: Software Development :: Build Tools
Classifier: Programming Language :: Python :: 3
Classifier: Programming Language :: Python :: 3.4
Classifier: Programming Language :: Python :: 3.5
Classifier: Programming Language :: Python :: 3.6
Classifier: License :: OSI Approved :: MIT License
Classifier: Operating System :: OS Independent
Requires-Python: >=3.6
